stockholm_aws_train/__init__.py
stockholm_aws_train-0.1.0.dist-info/WHEEL
stockholm_aws_train-0.1.0.dist-info/METADATA
stockholm_aws_train-0.1.0.dist-info/RECORD
