Metadata-Version: 2.1
Name: stockholm-aws-train
Version: 0.1.0
Summary: 
Author: Amresh Venugopal
Author-email: amresh.venugopal@gmail.com
Requires-Python: >=3.6,<4.0
Classifier: Programming Language :: Python :: 3
Classifier: Programming Language :: Python :: 3.6
Classifier: Programming Language :: Python :: 3.7
Classifier: Programming Language :: Python :: 3.8
Requires-Dist: boto3 (>=1.16.2,<2.0.0)
Requires-Dist: fabric (>=2.5.0,<3.0.0)
